{
    "last_refreshed": "Jun 24, 2024 02:16 PM",
    "index 0": {
        "Nonimmigrant Visa Type": "Interview Required Visitors (B1/B2)",
        "records": [
            {
                "Chennai (Madras)": "522 Days"
            },
            {
                "New Delhi": "210 Days"
            },
            {
                "Mumbai (Bombay)": "443 Days"
            },
            {
                "Kolkata": "373 Days"
            },
            {
                "Hyderabad": "506 Days"
            }
        ]
    }
}