{
    "last_refreshed": "Jul 05, 2024 08:18 AM",
    "index 0": {
        "Nonimmigrant Visa Type": "Interview Required Visitors (B1/B2)",
        "records": [
            {
                "Chennai (Madras)": "518 Days"
            },
            {
                "New Delhi": "218 Days"
            },
            {
                "Mumbai (Bombay)": "444 Days"
            },
            {
                "Kolkata": "367 Days"
            },
            {
                "Hyderabad": "429 Days"
            }
        ]
    }
}