{
    "last_refreshed": "Aug 04, 2025 11:24 AM",
    "index 0": {
        "Nonimmigrant Visa Type": "Interview Required Students/Exchange Visitors (F, M, J)",
        "records": [
            {
                "Chennai (Madras)": "44 Days"
            },
            {
                "New Delhi": "55 Days"
            },
            {
                "Mumbai (Bombay)": "86 Days"
            },
            {
                "Kolkata": "59 Days"
            },
            {
                "Hyderabad": "66 Days"
            }
        ]
    }
}